Workbook

Sheet 収入
A1: 日付 | B1: クライアント名 | C1: 案件名 | D1: 請求金額(税抜) | E1: 消費税(10%) | F1: 請求金額(税込) | G1: 入金日 | H1: 入金確認 | I1: 請求書番号 | J1: 備考
E2: =IF(D2="","",D2*0.1) | F2: =IF(D2="","",D2+E2)
E3: =IF(D3="","",D3*0.1) | F3: =IF(D3="","",D3+E3)
E4: =IF(D4="","",D4*0.1) | F4: =IF(D4="","",D4+E4)
E5: =IF(D5="","",D5*0.1) | F5: =IF(D5="","",D5+E5)
E6: =IF(D6="","",D6*0.1) | F6: =IF(D6="","",D6+E6)
E7: =IF(D7="","",D7*0.1) | F7: =IF(D7="","",D7+E7)
E8: =IF(D8="","",D8*0.1) | F8: =IF(D8="","",D8+E8)
E9: =IF(D9="","",D9*0.1) | F9: =IF(D9="","",D9+E9)
E10: =IF(D10="","",D10*0.1) | F10: =IF(D10="","",D10+E10)
E11: =IF(D11="","",D11*0.1) | F11: =IF(D11="","",D11+E11)
E12: =IF(D12="","",D12*0.1) | F12: =IF(D12="","",D12+E12)
E13: =IF(D13="","",D13*0.1) | F13: =IF(D13="","",D13+E13)
... E31: =IF(D31="","",D31*0.1) | F31: =IF(D31="","",D31+E31)
A32: 【月計】 | D32: =SUM(D2:D31) | E32: =SUM(E2:E31) | F32: =SUM(F2:F31)

Sheet 経費
A1: 日付 | B1: 科目 | C1: 金額 | D1: 支払方法 | E1: 摘要 | F1: レシートあり | H1: 科目 | I1: 合計
H2: 通信費 | I2: =SUMIF(B:B,"通信費",C:C)
H3: 交通費 | I3: =SUMIF(B:B,"交通費",C:C)
H4: ソフトウェア | I4: =SUMIF(B:B,"ソフトウェア",C:C)
H5: 書籍・研修 | I5: =SUMIF(B:B,"書籍・研修",C:C)
H6: 外注費 | I6: =SUMIF(B:B,"外注費",C:C)
H7: 消耗品 | I7: =SUMIF(B:B,"消耗品",C:C)
H8: 接待交際費 | I8: =SUMIF(B:B,"接待交際費",C:C)
H9: その他 | I9: =SUMIF(B:B,"その他",C:C)
H10: 合計 | I10: =SUM(I2:I9)

Sheet 案件管理
A1: 案件名 | B1: クライアント | C1: 単価(円) | D1: 稼働時間(h) | E1: 時給(自動) | F1: 開始日 | G1: 終了日 | H1: ステータス | I1: 備考
E2: =IF(OR(C2="",D2=0),"",C2/D2)
E3: =IF(OR(C3="",D3=0),"",C3/D3)
E4: =IF(OR(C4="",D4=0),"",C4/D4)
E5: =IF(OR(C5="",D5=0),"",C5/D5)
E6: =IF(OR(C6="",D6=0),"",C6/D6)
E7: =IF(OR(C7="",D7=0),"",C7/D7)
E8: =IF(OR(C8="",D8=0),"",C8/D8)
E9: =IF(OR(C9="",D9=0),"",C9/D9)
E10: =IF(OR(C10="",D10=0),"",C10/D10)
E11: =IF(OR(C11="",D11=0),"",C11/D11)
E12: =IF(OR(C12="",D12=0),"",C12/D12)
E13: =IF(OR(C13="",D13=0),"",C13/D13)
... E31: =IF(OR(C31="",D31=0),"",C31/D31)

Sheet 年間サマリー
A1: 2026年 収支サマリー
A3: 月 | B3: 収入(税抜) | C3: 経費 | D3: 手取り | E3: 前月比
A4: 1月 | B4: =SUMPRODUCT((MONTH(収入!A$2:A$200)=1)*(YEAR(収入!A$2:A$200)=YEAR(TODAY()))*収入!D$2:D$200) | C4: =SUMPRODUCT((MONTH(経費!A$2:A$200)=1)*(YEAR(経費!A$2:A$200)=YEAR(TODAY()))*経費!C$2:C$200) | D4: =B4-C4 | E4: =IF(ROW()-4<=1,"",D4-D3)
A5: 2月 | B5: =SUMPRODUCT((MONTH(収入!A$2:A$200)=2)*(YEAR(収入!A$2:A$200)=YEAR(TODAY()))*収入!D$2:D$200) | C5: =SUMPRODUCT((MONTH(経費!A$2:A$200)=2)*(YEAR(経費!A$2:A$200)=YEAR(TODAY()))*経費!C$2:C$200) | D5: =B5-C5 | E5: =IF(ROW()-4<=1,"",D5-D4)
A6: 3月 | B6: =SUMPRODUCT((MONTH(収入!A$2:A$200)=3)*(YEAR(収入!A$2:A$200)=YEAR(TODAY()))*収入!D$2:D$200) | C6: =SUMPRODUCT((MONTH(経費!A$2:A$200)=3)*(YEAR(経費!A$2:A$200)=YEAR(TODAY()))*経費!C$2:C$200) | D6: =B6-C6 | E6: =IF(ROW()-4<=1,"",D6-D5)
A7: 4月 | B7: =SUMPRODUCT((MONTH(収入!A$2:A$200)=4)*(YEAR(収入!A$2:A$200)=YEAR(TODAY()))*収入!D$2:D$200) | C7: =SUMPRODUCT((MONTH(経費!A$2:A$200)=4)*(YEAR(経費!A$2:A$200)=YEAR(TODAY()))*経費!C$2:C$200) | D7: =B7-C7 | E7: =IF(ROW()-4<=1,"",D7-D6)
A8: 5月 | B8: =SUMPRODUCT((MONTH(収入!A$2:A$200)=5)*(YEAR(収入!A$2:A$200)=YEAR(TODAY()))*収入!D$2:D$200) | C8: =SUMPRODUCT((MONTH(経費!A$2:A$200)=5)*(YEAR(経費!A$2:A$200)=YEAR(TODAY()))*経費!C$2:C$200) | D8: =B8-C8 | E8: =IF(ROW()-4<=1,"",D8-D7)
A9: 6月 | B9: =SUMPRODUCT((MONTH(収入!A$2:A$200)=6)*(YEAR(収入!A$2:A$200)=YEAR(TODAY()))*収入!D$2:D$200) | C9: =SUMPRODUCT((MONTH(経費!A$2:A$200)=6)*(YEAR(経費!A$2:A$200)=YEAR(TODAY()))*経費!C$2:C$200) | D9: =B9-C9 | E9: =IF(ROW()-4<=1,"",D9-D8)
A10: 7月 | B10: =SUMPRODUCT((MONTH(収入!A$2:A$200)=7)*(YEAR(収入!A$2:A$200)=YEAR(TODAY()))*収入!D$2:D$200) | C10: =SUMPRODUCT((MONTH(経費!A$2:A$200)=7)*(YEAR(経費!A$2:A$200)=YEAR(TODAY()))*経費!C$2:C$200) | D10: =B10-C10 | E10: =IF(ROW()-4<=1,"",D10-D9)
A11: 8月 | B11: =SUMPRODUCT((MONTH(収入!A$2:A$200)=8)*(YEAR(収入!A$2:A$200)=YEAR(TODAY()))*収入!D$2:D$200) | C11: =SUMPRODUCT((MONTH(経費!A$2:A$200)=8)*(YEAR(経費!A$2:A$200)=YEAR(TODAY()))*経費!C$2:C$200) | D11: =B11-C11 | E11: =IF(ROW()-4<=1,"",D11-D10)
A12: 9月 | B12: =SUMPRODUCT((MONTH(収入!A$2:A$200)=9)*(YEAR(収入!A$2:A$200)=YEAR(TODAY()))*収入!D$2:D$200) | C12: =SUMPRODUCT((MONTH(経費!A$2:A$200)=9)*(YEAR(経費!A$2:A$200)=YEAR(TODAY()))*経費!C$2:C$200) | D12: =B12-C12 | E12: =IF(ROW()-4<=1,"",D12-D11)
A13: 10月 | B13: =SUMPRODUCT((MONTH(収入!A$2:A$200)=10)*(YEAR(収入!A$2:A$200)=YEAR(TODAY()))*収入!D$2:D$200) | C13: =SUMPRODUCT((MONTH(経費!A$2:A$200)=10)*(YEAR(経費!A$2:A$200)=YEAR(TODAY()))*経費!C$2:C$200) | D13: =B13-C13 | E13: =IF(ROW()-4<=1,"",D13-D12)
A14: 11月 | B14: =SUMPRODUCT((MONTH(収入!A$2:A$200)=11)*(YEAR(収入!A$2:A$200)=YEAR(TODAY()))*収入!D$2:D$200) | C14: =SUMPRODUCT((MONTH(経費!A$2:A$200)=11)*(YEAR(経費!A$2:A$200)=YEAR(TODAY()))*経費!C$2:C$200) | D14: =B14-C14 | E14: =IF(ROW()-4<=1,"",D14-D13)
A15: 12月 | B15: =SUMPRODUCT((MONTH(収入!A$2:A$200)=12)*(YEAR(収入!A$2:A$200)=YEAR(TODAY()))*収入!D$2:D$200) | C15: =SUMPRODUCT((MONTH(経費!A$2:A$200)=12)*(YEAR(経費!A$2:A$200)=YEAR(TODAY()))*経費!C$2:C$200) | D15: =B15-C15 | E15: =IF(ROW()-4<=1,"",D15-D14)
A16: 年間合計 | B16: =SUM(B4:B15) | C16: =SUM(C4:C15) | D16: =SUM(D4:D15)
A18: 最高収入月 | B18: =TEXT(MATCH(MAX(B4:B15),B4:B15,0),"0")&"月" | C18: 最高額 | D18: =MAX(B4:B15)
A19: 最低収入月 | B19: =TEXT(MATCH(MIN(IF(B4:B15>0,B4:B15)),B4:B15,0),"0")&"月" | C19: 最低額 | D19: =MIN(IF(B4:B15>0,B4:B15))
